pyNeuroDAP/__init__.py
pyNeuroDAP/gui.py
pyNeuroDAP/mat.py
pyNeuroDAP/models.py
pyNeuroDAP/models_old.py
pyNeuroDAP/plots.py
pyNeuroDAP/sessions.py
pyNeuroDAP/spikes.py
pyNeuroDAP/trials.py
pyneurodap-1.1.0.dist-info/licenses/LICENSE
pyneurodap-1.1.0.dist-info/METADATA
pyneurodap-1.1.0.dist-info/WHEEL
pyneurodap-1.1.0.dist-info/top_level.txt
pyneurodap-1.1.0.dist-info/RECORD
