Metadata-Version: 2.4
Name: pyNeuroDAP
Version: 1.1.0
Summary: Neural Data Analysis Package for spike processing, trial management, and modeling
Home-page: https://github.com/shunnnli/pyNeuroDAP
Author: Shun Li
Author-email: Shun Li <shunli@g.harvard.edu>
Maintainer-email: Shun Li <shunli@g.harvard.edu>
License: MIT
Project-URL: Homepage, https://github.com/shunnnli/pyNeuroDAP
Project-URL: Documentation, https://github.com/shunnnli/pyNeuroDAP#readme
Project-URL: Repository, https://github.com/shunnnli/pyNeuroDAP
Project-URL: Bug Tracker, https://github.com/shunnnli/pyNeuroDAP/issues
Project-URL: Source Code, https://github.com/shunnnli/pyNeuroDAP
Keywords: neuroscience,neural data,spike analysis,electrophysiology,rSLDS,machine learning
Classifier: Development Status :: 3 - Alpha
Classifier: Intended Audience :: Science/Research
Classifier: Topic :: Scientific/Engineering :: Bio-Informatics
Classifier: Topic :: Scientific/Engineering :: Information Analysis
Classifier: Topic :: Scientific/Engineering :: Artificial Intelligence
Classifier: License :: OSI Approved :: MIT License
Classifier: Programming Language :: Python :: 3
Classifier: Programming Language :: Python :: 3.8
Classifier: Programming Language :: Python :: 3.9
Classifier: Programming Language :: Python :: 3.10
Classifier: Programming Language :: Python :: 3.11
Classifier: Programming Language :: Python :: 3.12
Classifier: Programming Language :: Python :: 3.13
Classifier: Operating System :: OS Independent
Classifier: Operating System :: MacOS
Classifier: Operating System :: Microsoft :: Windows
Classifier: Operating System :: POSIX :: Linux
Requires-Python: >=3.8
License-File: LICENSE
Requires-Dist: numpy>=1.20.0
Requires-Dist: scipy>=1.7.0
Requires-Dist: pandas>=1.3.0
Requires-Dist: matplotlib>=3.3.0
Requires-Dist: seaborn>=0.11.0
Requires-Dist: scikit-learn>=1.0.0
Requires-Dist: h5py>=3.0.0
Requires-Dist: tables>=3.7.0
Requires-Dist: tqdm>=4.60.0
Requires-Dist: dask>=2022.0.0
Requires-Dist: PySide6>=6.0.0
Provides-Extra: dev
Requires-Dist: pytest>=6.0; extra == "dev"
Requires-Dist: pytest-cov>=2.0; extra == "dev"
Requires-Dist: black>=21.0; extra == "dev"
Requires-Dist: flake8>=3.8; extra == "dev"
Requires-Dist: mypy>=0.800; extra == "dev"
Requires-Dist: pre-commit>=2.0; extra == "dev"
Provides-Extra: docs
Requires-Dist: sphinx>=4.0.0; extra == "docs"
Requires-Dist: sphinx-rtd-theme>=1.0.0; extra == "docs"
Requires-Dist: numpydoc>=1.1.0; extra == "docs"
Requires-Dist: myst-parser>=0.15.0; extra == "docs"
Provides-Extra: test
Requires-Dist: pytest>=6.0; extra == "test"
Requires-Dist: pytest-cov>=2.0; extra == "test"
Requires-Dist: pytest-mock>=3.0; extra == "test"
Provides-Extra: full
Requires-Dist: ssm>=0.3.0; extra == "full"
Requires-Dist: jax>=0.3.0; extra == "full"
Requires-Dist: jaxlib>=0.3.0; extra == "full"
Dynamic: author
Dynamic: home-page
Dynamic: license-file
Dynamic: requires-python
